libpkpass/__init__.py
libpkpass/_version.py
libpkpass/crypto.py
libpkpass/errors.py
libpkpass/escrow.py
libpkpass/identities.py
libpkpass/password.py
libpkpass/passworddb.py
libpkpass/util.py
libpkpass/commands/__init__.py
libpkpass/commands/arguments.py
libpkpass/commands/card.py
libpkpass/commands/cli.py
libpkpass/commands/clip.py
libpkpass/commands/command.py
libpkpass/commands/create.py
libpkpass/commands/delete.py
libpkpass/commands/distribute.py
libpkpass/commands/export.py
libpkpass/commands/fileimport.py
libpkpass/commands/generate.py
libpkpass/commands/info.py
libpkpass/commands/interpreter.py
libpkpass/commands/list.py
libpkpass/commands/listrecipients.py
libpkpass/commands/modify.py
libpkpass/commands/pkinterface.py
libpkpass/commands/populate.py
libpkpass/commands/recover.py
libpkpass/commands/rename.py
libpkpass/commands/show.py
libpkpass/commands/update.py
libpkpass/commands/verifyinstall.py
libpkpass/connectors/__init__.py
libpkpass/connectors/connectorinterface.py
libpkpass/models/__init__.py
libpkpass/models/cert.py
libpkpass/models/recipient.py
pkpass_olcf-2.9.4.data/scripts/pkpass
test/__init__.py
test/test_create.py
test/test_crypto.py
test/test_distribute.py
test/test_escrow.py
test/test_generate.py
test/test_id.py
test/test_info.py
test/test_list.py
test/test_list_recipients.py
test/test_modify.py
test/test_noop.py
test/test_password.py
test/test_passworddb.py
test/test_rename.py
test/test_show.py
test/test_update.py
test/basetest/__init__.py
test/basetest/basetest.py
pkpass_olcf-2.9.4.dist-info/LICENSE.md
pkpass_olcf-2.9.4.dist-info/METADATA
pkpass_olcf-2.9.4.dist-info/WHEEL
pkpass_olcf-2.9.4.dist-info/top_level.txt
pkpass_olcf-2.9.4.dist-info/RECORD
