Metadata-Version: 2.1
Name: pkpass-olcf
Version: 2.9.4
Summary: Public Key based Password Management
Home-page: https://github.com/olcf/pkpass
Author: Noah Ginsburg
Author-email: ginsburgnm@gmail.com
License: GPLV3
Classifier: Environment :: Console
Classifier: Intended Audience :: Developers
Classifier: Intended Audience :: Information Technology
Classifier: Intended Audience :: System Administrators
Classifier: License :: OSI Approved :: GNU General Public License v3 (GPLv3)
Classifier: Operating System :: OS Independent
Classifier: Programming Language :: Python :: 3.5
Classifier: Programming Language :: Python :: 3.6
Classifier: Programming Language :: Python :: 3.7
Classifier: Programming Language :: Python :: 3.8
Classifier: Topic :: Security :: Cryptography
License-File: LICENSE.md
Requires-Dist: PyYAML==6.0.2
Requires-Dist: SQLAlchemy==1.4.30
Requires-Dist: colored==1.4.4
Requires-Dist: cryptography==36.0.1
Requires-Dist: exrex==0.11.0
Requires-Dist: mock==4.0.3
Requires-Dist: pem==21.2.0
Requires-Dist: pylibyaml==0.1.0
Requires-Dist: pyperclip==1.8.2
Requires-Dist: pyseltongue==1.0.1
Requires-Dist: python-dateutil==2.8.2
Requires-Dist: ruamel.yaml.clib==0.2.8
Requires-Dist: ruamel.yaml==0.17.20
Requires-Dist: setuptools==65.5.1
Requires-Dist: tqdm==4.62.3
Provides-Extra: testing
Requires-Dist: mock; extra == "testing"
Requires-Dist: tox; extra == "testing"
